morphodynamics/__init__.py
morphodynamics/analysis_par.py
morphodynamics/correlation.py
morphodynamics/displacementestimation.py
morphodynamics/folders.py
morphodynamics/functionaldefinition.py
morphodynamics/morpho_segmentation.py
morphodynamics/segmentation.py
morphodynamics/splineutils.py
morphodynamics/syntheticdata.py
morphodynamics/utils.py
morphodynamics/version.py
morphodynamics/windowing.py
morphodynamics/data/__init__.py
morphodynamics/data/synth.py
morphodynamics/plots/__init__.py
morphodynamics/plots/animate_plots.py
morphodynamics/plots/show_plots.py
morphodynamics/plots/ui_wimage.py
morphodynamics/store/__init__.py
morphodynamics/store/dataset.py
morphodynamics/store/parameters.py
morphodynamics/store/results.py
morphodynamics-0.4.1.dist-info/LICENSE
morphodynamics-0.4.1.dist-info/METADATA
morphodynamics-0.4.1.dist-info/WHEEL
morphodynamics-0.4.1.dist-info/top_level.txt
morphodynamics-0.4.1.dist-info/RECORD
