Metadata-Version: 2.1
Name: morphodynamics
Version: 0.4.1
Summary: Cell segmentation and windowing
Home-page: https://github.com/guiwitz/morphodynamics
Author: Guillaume Witz and Cedric Vonesch
Author-email: guillaume.witz@unibe.ch
License: BSD 3-Clause
Classifier: Development Status :: 2 - Pre-Alpha
Classifier: Topic :: Software Development :: Testing
Classifier: Programming Language :: Python
Classifier: Programming Language :: Python :: 3
Classifier: Programming Language :: Python :: 3.9
Classifier: Programming Language :: Python :: 3.10
Classifier: Operating System :: OS Independent
Classifier: License :: OSI Approved :: BSD License
Requires-Python: <3.11,>=3.9
License-File: LICENSE
Requires-Dist: aicsimageio
Requires-Dist: dask[complete]
Requires-Dist: dask-jobqueue
Requires-Dist: napari-convpaint
Requires-Dist: numpy
Requires-Dist: pandas
Requires-Dist: matplotlib
Requires-Dist: scikit-image
Requires-Dist: tifffile
Requires-Dist: microfilm
Requires-Dist: dill
Requires-Dist: joblib
Requires-Dist: tqdm
Requires-Dist: ipywidgets
Requires-Dist: cmap
Provides-Extra: book
Requires-Dist: jupyter-book ; extra == 'book'
Requires-Dist: sphinx ; extra == 'book'
Provides-Extra: cellpose
Requires-Dist: cellpose ; extra == 'cellpose'
Provides-Extra: napari
Requires-Dist: napari[all] ; extra == 'napari'
Provides-Extra: nd2
Requires-Dist: nd2reader ; extra == 'nd2'
